snmpwalk_parser/__init__.py
snmpwalk_parser/cli.py
snmpwalk_parser/core.py
snmpwalk_parser/models.py
snmpwalk_parser/snmp_runner.py
snmpwalk_parser-1.0.1.dist-info/licenses/LICENSE
snmpwalk_parser-1.0.1.dist-info/METADATA
snmpwalk_parser-1.0.1.dist-info/WHEEL
snmpwalk_parser-1.0.1.dist-info/entry_points.txt
snmpwalk_parser-1.0.1.dist-info/top_level.txt
snmpwalk_parser-1.0.1.dist-info/RECORD
