Metadata-Version: 2.4
Name: snmpwalk-parser
Version: 1.0.1
Summary: A comprehensive SNMP parser package for extracting and analyzing SNMP walk data
Home-page: https://github.com/kunalraut/snmpwalk-parser
Author: Kunal Raut
Author-email: Kunal Raut <kunalraut489@gmail.com>
Maintainer-email: Kunal Raut <kunalraut489@gmail.com>
License: MIT
Project-URL: Homepage, https://github.com/kunalraut666/snmpwalk-parser
Project-URL: Documentation, https://snmpwalk-parser.readthedocs.io/
Project-URL: Repository, https://github.com/kunalraut666/snmpwalk-parser
Project-URL: Issues, https://github.com/kunalraut666/snmpwalk-parser/issues
Project-URL: Changelog, https://github.com/kunalraut666/snmpwalk-parser/blob/main/CHANGELOG.md
Keywords: snmp,snmpwalk,network,monitoring,parser,network-management,mib,oid,system-administration
Classifier: Development Status :: 4 - Beta
Classifier: Intended Audience :: Developers
Classifier: Intended Audience :: System Administrators
Classifier: License :: OSI Approved :: MIT License
Classifier: Operating System :: OS Independent
Classifier: Programming Language :: Python :: 3
Classifier: Programming Language :: Python :: 3.7
Classifier: Programming Language :: Python :: 3.8
Classifier: Programming Language :: Python :: 3.9
Classifier: Programming Language :: Python :: 3.10
Classifier: Programming Language :: Python :: 3.11
Classifier: Programming Language :: Python :: 3.12
Classifier: Topic :: System :: Networking
Classifier: Topic :: System :: Systems Administration
Classifier: Topic :: Software Development :: Libraries :: Python Modules
Requires-Python: >=3.7
License-File: LICENSE
Provides-Extra: dev
Requires-Dist: pytest>=6.0; extra == "dev"
Requires-Dist: pytest-cov>=2.0; extra == "dev"
Requires-Dist: black>=21.0; extra == "dev"
Requires-Dist: flake8>=3.8; extra == "dev"
Requires-Dist: mypy>=0.800; extra == "dev"
Requires-Dist: isort>=5.0; extra == "dev"
Requires-Dist: pre-commit>=2.0; extra == "dev"
Provides-Extra: docs
Requires-Dist: sphinx>=4.0; extra == "docs"
Requires-Dist: sphinx-rtd-theme>=1.0; extra == "docs"
Requires-Dist: myst-parser>=0.18; extra == "docs"
Provides-Extra: examples
Requires-Dist: matplotlib>=3.0; extra == "examples"
Requires-Dist: pandas>=1.0; extra == "examples"
Requires-Dist: jupyter>=1.0; extra == "examples"
Requires-Dist: plotly>=5.0; extra == "examples"
Provides-Extra: test
Requires-Dist: pytest>=6.0; extra == "test"
Requires-Dist: pytest-cov>=2.0; extra == "test"
Requires-Dist: pytest-mock>=3.0; extra == "test"
Requires-Dist: coverage>=6.0; extra == "test"
Dynamic: author
Dynamic: home-page
Dynamic: license-file
Dynamic: requires-python
